[
  {
    "number": "101",
    "name": "TVM",
    "code": "tvm",
    "type": "video-manifest",
    "manifest": "https://customer-ujex1meek7koqd9x.cloudflarestream.com/9e93379c0d46ee588b99263d95bd9c42/manifest/video.m3u8"
  },
  {
    "number": "102",
    "name": "PSM News",
    "code": "psm-news",
    "type": "video-manifest",
    "manifest": "https://customer-ujex1meek7koqd9x.cloudflarestream.com/21262545317dadfa20dab4f9bd37c7c2/manifest/video.m3u8"
  },
  {
    "number": "103",
    "name": "Maldives TV",
    "code": "mv-tv",
    "type": "video-manifest",
    "manifest": "https://live.maldivestv.mv/hls/stream/index.m3u8"
  },
  {
    "number": "104",
    "name": "Yes TV",
    "code": "yes-tv",
    "type": "video-manifest",
    "manifest": "https://customer-ujex1meek7koqd9x.cloudflarestream.com/4f0b316cdb0fbb7f8ca93860ed11d38b/manifest/video.m3u8"
  },
  {
    "number": "105",
    "name": "VTV",
    "code": "vtv",
    "type": "video-manifest",
    "manifest": "https://vtvstream.vnews.mv/vtvlive/vmedia/playlist.m3u8"
  },
  {
    "number": "106",
    "name": "SSTV",
    "code": "sstv",
    "type": "video-manifest",
    "manifest": "webrtc://159.65.10.45:80/live/livestream"
  },
  {
    "number": "107",
    "name": "Raajje TV",
    "code": "raajje-tv",
    "type": "video-manifest",
    "manifest": "https://stream.raajje.mv/live/rtv_live/index.m3u8"
  },
  {
    "number": "108",
    "name": "Channel 13",
    "code": "channel13",
    "type": "video-manifest",
    "manifest": "https://stream.theyraonline.com/live/channel13@live/index.m3u8"
  },
  {
    "number": "190",
    "name": "MakkahTV",
    "code": "makkah-tv",
    "type": "video-manifest",
    "manifest": "https://media2.streambrothers.com:1936/8122/8122/playlist.m3u8"
  },
  {
    "number": "201",
    "name": "NHK World",
    "code": "nhkworld",
    "type": "video-manifest",
    "manifest": "https://master.nhkworld.jp/nhkworld-tv/playlist/live.m3u8"
  },
  {
    "number": "202",
    "name": "Fashion tv 1",
    "code": "fashiontv-1-eu",
    "type": "video-manifest",
    "manifest":"https://fashiontv-fashiontv-1-eu.rakuten.wurl.tv/playlist.m3u8"
  },
  {
    "number": "203",
    "name": "BBC News",
    "code": "bbc-news-uk",
    "type": "video-manifest",
    "manifest": "https://vs-hls-push-ww-live.akamaized.net/x=4/i=urn:bbc:pips:service:bbc_news_channel_hd/t=3840/v=pv14/b=5070016/main.m3u8"
  },
  {
    "number": "901",
    "name": "Dhivehi FM",
    "code": "fmair",
    "type": "audio",
    "audio": "https://radio.psm.mv/fmair"
  },
  {
    "number": "902",
    "name": "Dhivehi Raajjeyge Adu",
    "code": "draair",
    "type": "audio",
    "audio": "https://radio.psm.mv/draair"
  },
  {
    "number": "903",
    "name": "Dheenuge Adu",
    "code": "dheenugeaduair",
    "type": "audio",
    "audio": "https://radio.psm.mv/dheenugeaduair"
  }
]
